{
  "types": {
    "1": "Italian",
    "2": "American",
    "3": "Mexican",
    "4": "Chinese",
    "5": "Tapas"
  },
  "services": {
    "1": "Takeaway",
    "2": "Dine"
  },
  "brands": {
    "1": {
      "name": "McDonalds",
      "service_type": [1, 2],
      "type_id": 2,
      "avg_rating": 3.4,
      "avg_cost": "14",
      "currency": "GBP",
      "locations": [{
          "name": "Portsmouth",
          "opening_date": "date to go here"
        }, {
          "name": "Maidstone",
          "opening_date": "date to go here"
        }, {
          "name": "Maidstone",
          "opening_date": "date to go here"
        }],
      "keywords": ["Fast Food","Unhealthy","Burgers", "Fries", "Chips", "Beef", "Fried"]
    },
    "2": {
      "name": "KFC",
      "service_type": [2],
      "type_id": 2,
      "avg_rating": 3.5,
      "avg_cost": "15",
      "currency": "GBP",
      "locations": [{
          "name": "Portsmouth",
          "opening_date": "date to go here"
        }, {
          "name": "Maidstone",
          "opening_date": "date to go here"
        }, {
          "name": "Cheltenham",
          "opening_date": "date to go here"
        }],
      "keywords": ["Fast Food","Unhealthy","Chicken", "Fries", "Chips", "Beef", "Fried"]
    },
    "3": {
      "name": "Joe's Pizza",
      "service_type": [2],
      "type_id": 2,
      "avg_rating": 3.2,
      "avg_cost": "19",
      "currency": "GBP",
      "locations": ["Portsmouth"],
      "locations": [{
          "name": "Portsmouth",
          "opening_date": "date to go here"
        }],
      "keywords": ["Authentic","Pizza","Pasta", "Ice Cream", "Gelato", "bread", "tomatoe"]
    },
    "4": {
      "name": "Del Taco",
      "service_type": [1, 2],
      "type_id": 3,
      "avg_rating": 4,
      "avg_cost": "19",
      "currency": "GBP",
      "locations": [{
          "name": "Yucaipa",
          "opening_date": "date to go here"
        }],
      "keywords": ["Authentic","Pizza","Pasta", "Ice Cream", "Gelato", "bread", "tomatoe"]
    },
    "5": {
      "name": "The New Restaurant",
      "service_type": [1, 2],
      "type_id": 3,
      "avg_rating": 0,
      "avg_cost": "19",
      "currency": "GBP",
      "locations": [{
          "name": "Portsmouth",
          "opening_date": "date to go here"
        }],
      "keywords": ["Tapas"]
    }
  }
}
